{
  "type": "FeatureCollection",
  "features": [
    {
      "type": "Feature",
      "properties": {
        "name": "Lpu data"
      },
      "geometry": {
        "coordinates": [
          [
            [
              75.70533928814098,
              31.251298689531467
            ],
            [
              75.70533928814098,
              31.25075018221918
            ],
            [
              75.70610890587787,
              31.25075018221918
            ],
            [
              75.70610890587787,
              31.251298689531467
            ],
            [
              75.70533928814098,
              31.251298689531467
            ]
          ]
        ],
        "type": "Polygon"
      }
    },
    {
      "type": "Feature",
      "properties": {
        "name": "Innovation Studio"
      },
      "geometry": {
        "coordinates": [
          75.705679138834,
          31.251075899371372
        ],
        "type": "Point"
      },
      "id": 1
    },
    {
      "type": "Feature",
      "properties": {},
      "geometry": {
        "coordinates": [
          [
            [
              75.70534398540315,
              31.251291745996227
            ],
            [
              75.70533588654709,
              31.250765542315776
            ],
            [
              75.70610122843263,
              31.25076208044058
            ],
            [
              75.7061174261448,
              31.251288284140344
            ],
            [
              75.70534398540315,
              31.251291745996227
            ]
          ]
        ],
        "type": "Polygon"
      }
    },
    {
      "type": "Feature",
      "properties": {},
      "geometry": {
        "coordinates": [
          [
            [
              75.70411378830997,
              31.255688185804942
            ],
            [
              75.70544990086299,
              31.255667345181152
            ],
            [
              75.70548376281937,
              31.255685158872012
            ],
            [
              75.70559186060288,
              31.25592453002021
            ],
            [
              75.70559186060288,
              31.25595236383488
            ],
            [
              75.7055619963875,
              31.25598303556484
            ],
            [
              75.70552044091929,
              31.255990140367146
            ],
            [
              75.70489918666567,
              31.25590133030225
            ],
            [
              75.7042010547944,
              31.255801862930184
            ],
            [
              75.70415118823232,
              31.255787653296792
            ],
            [
              75.70411378830997,
              31.255688185804942
            ]
          ]
        ],
        "type": "Polygon"
      }
    },
    {
      "type": "Feature",
      "properties": {
        "name": "Unimall"
      },
      "geometry": {
        "coordinates": [
          75.70496877661955,
          31.25579754632264
        ],
        "type": "Point"
      },
      "id": 4
    },
    {
      "type": "Feature",
      "properties": {
        "name": "Central Library"
      },
      "geometry": {
        "coordinates": [
          75.70366534476443,
          31.251932936454736
        ],
        "type": "Point"
      },
      "id": 5
    },
    {
      "type": "Feature",
      "properties": {
        "name": "BH - 5"
      },
      "geometry": {
        "coordinates": [
          75.70360622954132,
          31.248759007827445
        ],
        "type": "Point"
      },
      "id": 6
    }
  ]
}
